olympusphotosync/__init__.py
olympusphotosync/__main__.py
olympusphotosync/cli.py
olympusphotosync/gui.py
olympusphotosync/oishare.py
olympusphotosync/utils.py
olympus_photosync-1.4.0.dist-info/LICENSE
olympus_photosync-1.4.0.dist-info/METADATA
olympus_photosync-1.4.0.dist-info/WHEEL
olympus_photosync-1.4.0.dist-info/entry_points.txt
olympus_photosync-1.4.0.dist-info/top_level.txt
olympus_photosync-1.4.0.dist-info/RECORD
