Metadata-Version: 2.1
Name: olympus-photosync
Version: 1.4.0
Summary: Sync photos from WiFi enabled Olympus cameras
Author-email: Georgi Valkov <georgi.t.valkov@gmail.com>
Project-URL: Homepage, https://github.com/gvalkov/olympus-photosync
Keywords: olympus,camera,sync
Classifier: Development Status :: 5 - Production/Stable
Classifier: Programming Language :: Python :: 3
Classifier: License :: OSI Approved :: BSD License
Requires-Python: >=3.6
License-File: LICENSE
Requires-Dist: tqdm
